genriesz/__init__.py
genriesz/basis.py
genriesz/bregman.py
genriesz/dml.py
genriesz/estimate_functional.py
genriesz/functionals.py
genriesz/glm.py
genriesz/grr.py
genriesz/knn_basis.py
genriesz/sklearn_basis.py
genriesz/torch_basis.py
genriesz-0.1.9.dist-info/licenses/LICENSE
grr/__init__.py
grr/grr.py
grr/nn_grr.py
grr/rkhs_grr.py
grr/utils/NN_avgmom_sim.py
grr/utils/RF_avgmom_sim.py
grr/utils/__init__.py
grr/utils/forestriesz.py
grr/utils/ihdp_data.py
grr/utils/moments.py
grr/utils/oadam.py
grr/utils/riesznet.py
genriesz-0.1.9.dist-info/METADATA
genriesz-0.1.9.dist-info/WHEEL
genriesz-0.1.9.dist-info/top_level.txt
genriesz-0.1.9.dist-info/RECORD
