Metadata-Version: 2.4
Name: genriesz
Version: 0.1.9
Summary: Generalized Riesz Regression under Bregman divergences
Author: Masahiro Kato
License:                     GNU GENERAL PUBLIC LICENSE
Project-URL: Documentation, https://genriesz.readthedocs.io
Keywords: causal inference,debiased machine learning,riesz representer,bregman divergence
Classifier: License :: OSI Approved :: MIT License
Classifier: Programming Language :: Python :: 3
Classifier: Programming Language :: Python :: 3 :: Only
Classifier: Programming Language :: Python :: 3.10
Classifier: Programming Language :: Python :: 3.11
Classifier: Programming Language :: Python :: 3.12
Classifier: Intended Audience :: Science/Research
Classifier: Topic :: Scientific/Engineering
Requires-Python: >=3.10
License-File: LICENSE
Requires-Dist: numpy>=1.22
Requires-Dist: scipy>=1.9
Provides-Extra: torch
Requires-Dist: torch>=2.0; extra == "torch"
Provides-Extra: sklearn
Requires-Dist: scikit-learn>=1.2; extra == "sklearn"
Provides-Extra: docs
Requires-Dist: sphinx>=7; extra == "docs"
Requires-Dist: sphinx-rtd-theme>=2; extra == "docs"
Requires-Dist: sphinx-autodoc-typehints>=2; extra == "docs"
Provides-Extra: dev
Requires-Dist: pytest>=7; extra == "dev"
Requires-Dist: ruff>=0.5; extra == "dev"
Requires-Dist: build>=1.2; extra == "dev"
Requires-Dist: twine>=5; extra == "dev"
Dynamic: license-file
